Workbook

Sheet Raw_Dataset
A1: Month | B1: Product | C1: Actual Monthly Sales (units) | D1: Previous Company Forecast (units) | E1: Defect Rate (%) | F1: Labour Hours | G1: Available Production Capacity (units) | H1: Unit Production Cost (EGP) | I1: Unit Selling Price (EGP) | J1: Profit
A2: Jan | B2: Nile Espresso | C2: 4200 | D2: 4000 | E2: 2.8 | F2: 420 | G2: 5000 | H2: 180 | I2: 300 | J2: =I2-H2 -> 120
A3: Feb | B3: Nile Espresso | C3: 4000 | D3: 4200 | E3: 2.5 | F3: 400 | G3: 5000 | H3: 180 | I3: 300 | J3: =I3-H3 -> 120
A4: Mar | B4: Nile Espresso | C4: 4600 | D4: 4300 | E4: 3.1 | F4: 460 | G4: 5000 | H4: 180 | I4: 300 | J4: =I4-H4 -> 120
A5: Apr | B5: Nile Espresso | C5: 4800 | D5: 4700 | E5: 3.8 | F5: 480 | G5: 5000 | H5: 180 | I5: 300 | J5: =I5-H5 -> 120
A6: May | B6: Nile Espresso | C6: 5200 | D6: 4900 | E6: 3.4 | F6: 520 | G6: 5000 | H6: 180 | I6: 300 | J6: =I6-H6 -> 120
A7: Jun | B7: Nile Espresso | C7: 5600 | D7: 5400 | E7: 4.2 | F7: 560 | G7: 5500 | H7: 185 | I7: 300 | J7: =I7-H7 -> 115
A8: Jul | B8: Nile Espresso | C8: 6100 | D8: 5800 | E8: 4.8 | F8: 610 | G8: 5500 | H8: 185 | I8: 300 | J8: =I8-H8 -> 115
A9: Aug | B9: Nile Espresso | C9: 5900 | D9: 6200 | E9: 4.1 | F9: 590 | G9: 5500 | H9: 185 | I9: 300 | J9: =I9-H9 -> 115
A10: Sep | B10: Nile Espresso | C10: 5500 | D10: 5700 | E10: 3.6 | F10: 550 | G10: 5500 | H10: 185 | I10: 300 | J10: =I10-H10 -> 115
A11: Oct | B11: Nile Espresso | C11: 6200 | D11: 5800 | E11: 5.2 | F11: 620 | G11: 6000 | H11: 190 | I11: 300 | J11: =I11-H11 -> 110
A12: Nov | B12: Nile Espresso | C12: 6800 | D12: 6500 | E12: 4.7 | F12: 680 | G12: 6000 | H12: 190 | I12: 300 | J12: =I12-H12 -> 110
A13: Dec | B13: Nile Espresso | C13: 7600 | D13: 7200 | E13: 5.8 | F13: 760 | G13: 6000 | H13: 190 | I13: 300 | J13: =I13-H13 -> 110
... A37: Dec | B37: Nile Cold Brew | C37: 7800 | D37: 7000 | E37: 6.5 | F37: 936 | G37: 4500 | H37: 105 | I37: 170 | J37: =I37-H37 -> 65

Sheet PivotTables
A3: Sum of Actual Monthly Sales (units) | B3: Column Labels
A4: Row Labels | B4: Cairo House Blend | C4: Nile Cold Brew | D4: Nile Espresso | E4: Grand Total | H4: Row Labels | I4: Sum of Actual Monthly Sales (units)
A5: Jan | B5: 6000 | C5: 2500 | D5: 4200 | E5: 12700 | H5: Cairo House Blend | I5: 91300
A6: Feb | B6: 5800 | C6: 2300 | D6: 4000 | E6: 12100 | H6: Nile Cold Brew | I6: 53900
A7: Mar | B7: 6500 | C7: 3000 | D7: 4600 | E7: 14100 | H7: Nile Espresso | I7: 66500
A8: Apr | B8: 6800 | C8: 3400 | D8: 4800 | E8: 15000 | H8: Grand Total | I8: 211700
A9: May | B9: 7200 | C9: 3900 | D9: 5200 | E9: 16300
A10: Jun | B10: 7600 | C10: 4500 | D10: 5600 | E10: 17700
A11: Jul | B11: 8200 | C11: 5200 | D11: 6100 | E11: 19500
A12: Aug | B12: 8000 | C12: 5000 | D12: 5900 | E12: 18900 | H12: Row Labels | I12: Sum of Profit
A13: Sep | B13: 7500 | C13: 4200 | D13: 5500 | E13: 17200 | H13: Cairo House Blend | I13: 910
A14: Oct | B14: 8400 | C14: 5600 | D14: 6200 | E14: 20200 | H14: Nile Cold Brew | I14: 850
A15: Nov | B15: 9100 | C15: 6500 | D15: 6800 | E15: 22400 | H15: Nile Espresso | I15: 1390
A16: Dec | B16: 10200 | C16: 7800 | D16: 7600 | E16: 25600 | H16: Grand Total | I16: 3150
A17: Grand Total | B17: 91300 | C17: 53900 | D17: 66500 | E17: 211700
H19: Row Labels | I19: Sum of Unit Selling Price (EGP)
H20: Cairo House Blend | I20: 2280
H21: Nile Cold Brew | I21: 2040
H22: Nile Espresso | I22: 3600
H23: Grand Total | I23: 7920
H26: Row Labels | I26: Sum of Unit Production Cost (EGP)
H27: Cairo House Blend | I27: 1370
H28: Nile Cold Brew | I28: 1190
H29: Nile Espresso | I29: 2210
H30: Grand Total | I30: 4770
H33: Row Labels | I33: Sum of Available Production Capacity (units)
H34: Cairo House Blend | I34: 89000
H35: Nile Cold Brew | I35: 45500
H36: Nile Espresso | I36: 65000
H37: Grand Total | I37: 199500
H40: Row Labels | I40: Sum of Actual Monthly Sales (units) | J40: Sum of Previous Company Forecast (units)
H41: Jan | I41: 12700 | J41: 12900
H42: Feb | I42: 12100 | J42: 12500
H43: Mar | I43: 14100 | J43: 13300
H44: Apr | I44: 15000 | J44: 14500
H45: May | I45: 16300 | J45: 15500
H46: Jun | I46: 17700 | J46: 17000
H47: Jul | I47: 19500 | J47: 18500
H48: Aug | I48: 18900 | J48: 19900
H49: Sep | I49: 17200 | J49: 18100
H50: Oct | I50: 20200 | J50: 18900
H51: Nov | I51: 22400 | J51: 21400
H52: Dec | I52: 25600 | J52: 23900
H53: Grand Total | I53: 211700 | J53: 206400
A61: Sum of Actual Monthly Sales (units) | B61: Column Labels
A62: Row Labels | B62: Cairo House Blend | C62: Nile Cold Brew | D62: Nile Espresso | E62: Grand Total
A63: Jan | B63: 6000 | C63: 2500 | D63: 4200 | E63: 12700
A64: Feb | B64: 5800 | C64: 2300 | D64: 4000 | E64: 12100
A65: Mar | B65: 6500 | C65: 3000 | D65: 4600 | E65: 14100
A66: Apr | B66: 6800 | C66: 3400 | D66: 4800 | E66: 15000
A67: May | B67: 7200 | C67: 3900 | D67: 5200 | E67: 16300
A68: Jun | B68: 7600 | C68: 4500 | D68: 5600 | E68: 17700
A69: Jul | B69: 8200 | C69: 5200 | D69: 6100 | E69: 19500
A70: Aug | B70: 8000 | C70: 5000 | D70: 5900 | E70: 18900
A71: Sep | B71: 7500 | C71: 4200 | D71: 5500 | E71: 17200
A72: Oct | B72: 8400 | C72: 5600 | D72: 6200 | E72: 20200
A73: Nov | B73: 9100 | C73: 6500 | D73: 6800 | E73: 22400
A74: Dec | B74: 10200 | C74: 7800 | D74: 7600 | E74: 25600
A75: Grand Total | B75: 91300 | C75: 53900 | D75: 66500 | E75: 211700

Sheet Dashboard
A2: Nile Coffee — Dashboard Analysis

Sheet Demand Forecasting
A2: Nile Espresso — Demand analysis and forecasting
A4: Period | B4: Sales (units) | C4: Month
A5: 1 | B5: =SUMIFS(Raw_Dataset!$C$2:$C$37,Raw_Dataset!$A$2:$A$37,C5,Raw_Dataset!$B$2:$B$37,"Nile Espresso") -> 4200 | C5: Jan
A6: 2 | B6: =SUMIFS(Raw_Dataset!$C$2:$C$37,Raw_Dataset!$A$2:$A$37,C6,Raw_Dataset!$B$2:$B$37,"Nile Espresso") -> 4000 | C6: Feb
A7: 3 | B7: =SUMIFS(Raw_Dataset!$C$2:$C$37,Raw_Dataset!$A$2:$A$37,C7,Raw_Dataset!$B$2:$B$37,"Nile Espresso") -> 4600 | C7: Mar
A8: 4 | B8: =SUMIFS(Raw_Dataset!$C$2:$C$37,Raw_Dataset!$A$2:$A$37,C8,Raw_Dataset!$B$2:$B$37,"Nile Espresso") -> 4800 | C8: Apr
A9: 5 | B9: =SUMIFS(Raw_Dataset!$C$2:$C$37,Raw_Dataset!$A$2:$A$37,C9,Raw_Dataset!$B$2:$B$37,"Nile Espresso") -> 5200 | C9: May
A10: 6 | B10: =SUMIFS(Raw_Dataset!$C$2:$C$37,Raw_Dataset!$A$2:$A$37,C10,Raw_Dataset!$B$2:$B$37,"Nile Espresso") -> 5600 | C10: Jun
A11: 7 | B11: =SUMIFS(Raw_Dataset!$C$2:$C$37,Raw_Dataset!$A$2:$A$37,C11,Raw_Dataset!$B$2:$B$37,"Nile Espresso") -> 6100 | C11: Jul
A12: 8 | B12: =SUMIFS(Raw_Dataset!$C$2:$C$37,Raw_Dataset!$A$2:$A$37,C12,Raw_Dataset!$B$2:$B$37,"Nile Espresso") -> 5900 | C12: Aug
A13: 9 | B13: =SUMIFS(Raw_Dataset!$C$2:$C$37,Raw_Dataset!$A$2:$A$37,C13,Raw_Dataset!$B$2:$B$37,"Nile Espresso") -> 5500 | C13: Sep
A14: 10 | B14: =SUMIFS(Raw_Dataset!$C$2:$C$37,Raw_Dataset!$A$2:$A$37,C14,Raw_Dataset!$B$2:$B$37,"Nile Espresso") -> 6200 | C14: Oct
A15: 11 | B15: =SUMIFS(Raw_Dataset!$C$2:$C$37,Raw_Dataset!$A$2:$A$37,C15,Raw_Dataset!$B$2:$B$37,"Nile Espresso") -> 6800 | C15: Nov
A16: 12 | B16: =SUMIFS(Raw_Dataset!$C$2:$C$37,Raw_Dataset!$A$2:$A$37,C16,Raw_Dataset!$B$2:$B$37,"Nile Espresso") -> 7600 | C16: Dec
A19: Simple moving average | F19: Window (months): | J19: =INDEX(D98:H98,1,MATCH(MIN(D108:H108),D108:H108,0)) -> 2
A21: Period | B21: Demand | D21: Forecast | E21: Error (A-F) | F21: |Error| | G21: Error^2
A22: =A5 -> 1 | B22: =B5 -> 4200 | J22: n | K22: =COUNT(E28:E33) -> 6
A23: =A6 -> 2 | B23: =B6 -> 4000 | J23: Sum absolute errors | K23: =SUM(F28:F33) -> 3800
A24: =A7 -> 3 | B24: =B7 -> 4600 | J24: Sum squared errors | K24: =SUM(G28:G33) -> 3105000
A25: =A8 -> 4 | B25: =B8 -> 4800
A26: =A9 -> 5 | B26: =B9 -> 5200
A27: =A10 -> 6 | B27: =B10 -> 5600 | J27: MAD | K27: =K23/K22 -> 633.33333
A28: =A11 -> 7 | B28: =B11 -> 6100 | D28: =INDEX(D100:H100,1,MATCH($J$19,$D$98:$H$98,0)) -> 5400 | E28: =B28-D28 -> 700 | F28: =ABS(E28) -> 700 | G28: =E28^2 -> 490000 | J28: MSE | K28: =K24/K22 -> 517500
A29: =A12 -> 8 | B29: =B12 -> 5900 | D29: =INDEX(D101:H101,1,MATCH($J$19,$D$98:$H$98,0)) -> 5850 | E29: =B29-D29 -> 50 | F29: =ABS(E29) -> 50 | G29: =E29^2 -> 2500
A30: =A13 -> 9 | B30: =B13 -> 5500 | D30: =INDEX(D102:H102,1,MATCH($J$19,$D$98:$H$98,0)) -> 6000 | E30: =B30-D30 -> -500 | F30: =ABS(E30) -> 500 | G30: =E30^2 -> 250000
A31: =A14 -> 10 | B31: =B14 -> 6200 | D31: =INDEX(D103:H103,1,MATCH($J$19,$D$98:$H$98,0)) -> 5700 | E31: =B31-D31 -> 500 | F31: =ABS(E31) -> 500 | G31: =E31^2 -> 250000
A32: =A15 -> 11 | B32: =B15 -> 6800 | D32: =INDEX(D104:H104,1,MATCH($J$19,$D$98:$H$98,0)) -> 5850 | E32: =B32-D32 -> 950 | F32: =ABS(E32) -> 950 | G32: =E32^2 -> 902500
A33: =A16 -> 12 | B33: =B16 -> 7600 | D33: =INDEX(D105:H105,1,MATCH($J$19,$D$98:$H$98,0)) -> 6500 | E33: =B33-D33 -> 1100 | F33: =ABS(E33) -> 1100 | G33: =E33^2 -> 1210000
A36: Linear Trend
A38: Period | B38: Demand | D38: Forecast | E38: Error (A-F) | F38: |Error| | G38: Error^2
A39: =A5 -> 1 | B39: =B5 -> 4200 | J39: n | K39: =COUNT(E45:E50) -> 6
A40: =A6 -> 2 | B40: =B6 -> 4000 | J40: Sum absolute errors | K40: =SUM(F45:F50) -> 2749.5238
A41: =A7 -> 3 | B41: =B7 -> 4600 | J41: Sum squared errors | K41: =SUM(G45:G50) -> 1741468.6
A42: =A8 -> 4 | B42: =B8 -> 4800
A43: =A9 -> 5 | B43: =B9 -> 5200
A44: =A10 -> 6 | B44: =B10 -> 5600 | J44: MAD | K44: =K40/K39 -> 458.25397
A45: =A11 -> 7 | B45: =B11 -> 6100 | D45: =INTERCEPT($B$54:B59,$A$54:A59)+SLOPE($B$54:B59,$A$54:A59)*A45 -> 5813.3333 | E45: =B45-D45 -> 286.66667 | F45: =ABS(E45) -> 286.66667 | G45: =E45^2 -> 82177.778 | J45: MSE | K45: =K41/K39 -> 290244.77
A46: =A12 -> 8 | B46: =B12 -> 5900 | D46: =INTERCEPT($B$54:B60,$A$54:A60)+SLOPE($B$54:B60,$A$54:A60)*A46 -> 6285.7143 | E46: =B46-D46 -> -385.71429 | F46: =ABS(E46) -> 385.71429 | G46: =E46^2 -> 148775.51
A47: =A13 -> 9 | B47: =B13 -> 5500 | D47: =INTERCEPT($B$54:B61,$A$54:A61)+SLOPE($B$54:B61,$A$54:A61)*A47 -> 6432.1429 | E47: =B47-D47 -> -932.14286 | F47: =ABS(E47) -> 932.14286 | G47: =E47^2 -> 868890.31
A48: =A14 -> 10 | B48: =B14 -> 6200 | D48: =INTERCEPT($B$54:B62,$A$54:A62)+SLOPE($B$54:B62,$A$54:A62)*A48 -> 6325 | E48: =B48-D48 -> -125 | F48: =ABS(E48) -> 125 | G48: =E48^2 -> 15625
A49: =A15 -> 11 | B49: =B15 -> 6800 | D49: =INTERCEPT($B$54:B63,$A$54:A63)+SLOPE($B$54:B63,$A$54:A63)*A49 -> 6520 | E49: =B49-D49 -> 280 | F49: =ABS(E49) -> 280 | G49: =E49^2 -> 78400
A50: =A16 -> 12 | B50: =B16 -> 7600 | D50: =INTERCEPT($B$54:B64,$A$54:A64)+SLOPE($B$54:B64,$A$54:A64)*A50 -> 6860 | E50: =B50-D50 -> 740 | F50: =ABS(E50) -> 740 | G50: =E50^2 -> 547600
A53: Period | B53: Demand | C53: ty | D53: t^2
A54: =A5 -> 1 | B54: =B5 -> 4200 | C54: =A54*B54 -> 4200 | D54: =A54^2 -> 1
A55: =A6 -> 2 | B55: =B6 -> 4000 | C55: =A55*B55 -> 8000 | D55: =A55^2 -> 4
A56: =A7 -> 3 | B56: =B7 -> 4600 | C56: =A56*B56 -> 13800 | D56: =A56^2 -> 9
A57: =A8 -> 4 | B57: =B8 -> 4800 | C57: =A57*B57 -> 19200 | D57: =A57^2 -> 16
A58: =A9 -> 5 | B58: =B9 -> 5200 | C58: =A58*B58 -> 26000 | D58: =A58^2 -> 25
A59: =A10 -> 6 | B59: =B10 -> 5600 | C59: =A59*B59 -> 33600 | D59: =A59^2 -> 36
A60: =A11 -> 7 | B60: =B11 -> 6100 | C60: =A60*B60 -> 42700 | D60: =A60^2 -> 49
A61: =A12 -> 8 | B61: =B12 -> 5900 | C61: =A61*B61 -> 47200 | D61: =A61^2 -> 64
A62: =A13 -> 9 | B62: =B13 -> 5500 | C62: =A62*B62 -> 49500 | D62: =A62^2 -> 81
A63: =A14 -> 10 | B63: =B14 -> 6200 | C63: =A63*B63 -> 62000 | D63: =A63^2 -> 100
A64: =A15 -> 11 | B64: =B15 -> 6800 | C64: =A64*B64 -> 74800 | D64: =A64^2 -> 121
A65: =A16 -> 12 | B65: =B16 -> 7600 | C65: =A65*B65 -> 91200 | D65: =A65^2 -> 144
A68: n | B68: =COUNT(A54:A65) -> 12 | D68: b | E68: =(B68*B71-B69*B70)/(B68*B72-B73) -> 279.37063
A69: Sum t | B69: =SUM(A54:A65) -> 78 | D69: a | E69: =(B70-E68*B69)/B68 -> 3725.7576
A70: Sum y | B70: =SUM(B54:B65) -> 66500
A71: Sum ty | B71: =SUM(C54:C65) -> 472200
A72: Sum t² | B72: =SUM(D54:D65) -> 650
A73: (Sum t)² | B73: =B69^2 -> 6084
A75: Summary table
D77: Moving average | E77: Linear trend | F77: Company forecast
C78: MAD | D78: =K27 -> 633.33333 | E78: =K44 -> 458.25397 | F78: =AVERAGE(M100:M105) -> 316.66667
C79: MSE | D79: =K28 -> 517500 | E79: =K45 -> 290244.77 | F79: =AVERAGE(N100:N105) -> 105000
A83: Next six months — forecast demand (units)
A85: Period | B85: Month | C85: Moving average | D85: Linear trend | E85: Selected forecast | F85: Method
A86: 13 | B86: Jan (next year) | C86: =CHOOSE($J$19-1,AVERAGE(B15:B16),AVERAGE(B14:B16),AVERAGE(B13:B16),AVERAGE(B12:B16),AVERAGE(B11:B16)) -> 7200 | D86: =$E$69+$E$68*A86 -> 7357.5758 | E86: =ROUND(D86,0) -> 7358 | F86: Linear trend
A87: 14 | B87: Feb (next year) | C87: =CHOOSE($J$19-1,AVERAGE(B15:B16),AVERAGE(B14:B16),AVERAGE(B13:B16),AVERAGE(B12:B16),AVERAGE(B11:B16)) -> 7200 | D87: =$E$69+$E$68*A87 -> 7636.9464 | E87: =ROUND(D87,0) -> 7637 | F87: Linear trend
A88: 15 | B88: Mar (next year) | C88: =CHOOSE($J$19-1,AVERAGE(B15:B16),AVERAGE(B14:B16),AVERAGE(B13:B16),AVERAGE(B12:B16),AVERAGE(B11:B16)) -> 7200 | D88: =$E$69+$E$68*A88 -> 7916.317 | E88: =ROUND(D88,0) -> 7916 | F88: Linear trend
A89: 16 | B89: Apr (next year) | C89: =CHOOSE($J$19-1,AVERAGE(B15:B16),AVERAGE(B14:B16),AVERAGE(B13:B16),AVERAGE(B12:B16),AVERAGE(B11:B16)) -> 7200 | D89: =$E$69+$E$68*A89 -> 8195.6876 | E89: =ROUND(D89,0) -> 8196 | F89: Linear trend
A90: 17 | B90: May (next year) | C90: =CHOOSE($J$19-1,AVERAGE(B15:B16),AVERAGE(B14:B16),AVERAGE(B13:B16),AVERAGE(B12:B16),AVERAGE(B11:B16)) -> 7200 | D90: =$E$69+$E$68*A90 -> 8475.0583 | E90: =ROUND(D90,0) -> 8475 | F90: Linear trend
A91: 18 | B91: Jun (next year) | C91: =CHOOSE($J$19-1,AVERAGE(B15:B16),AVERAGE(B14:B16),AVERAGE(B13:B16),AVERAGE(B12:B16),AVERAGE(B11:B16)) -> 7200 | D91: =$E$69+$E$68*A91 -> 8754.4289 | E91: =ROUND(D91,0) -> 8754 | F91: Linear trend
A96: Window selection and previous-company-forecast comparison — July to December
D98: 2 | E98: 3 | F98: 4 | G98: 5 | H98: 6
A99: Period | B99: Month | C99: Actual | D99: MA(2) | E99: MA(3) | F99: MA(4) | G99: MA(5) | H99: MA(6) | J99: Actual | K99: Company forecast | L99: Error (A−F) | M99: Absolute error | N99: Squared error
A100: =A11 -> 7 | B100: Jul | C100: =B11 -> 6100 | D100: =AVERAGE(B9:B10) -> 5400 | E100: =AVERAGE(B8:B10) -> 5200 | F100: =AVERAGE(B7:B10) -> 5050 | G100: =AVERAGE(B6:B10) -> 4840 | H100: =AVERAGE(B5:B10) -> 4733.3333 | J100: =C100 -> 6100 | K100: =SUMIFS(Raw_Dataset!$D$2:$D$37,Raw_Dataset!$A$2:$A$37,B100,Raw_Dataset!$B$2:$B$37,"Nile Espresso") -> 5800 | L100: =J100-K100 -> 300 | M100: =ABS(L100) -> 300 | N100: =L100^2 -> 90000
A101: =A12 -> 8 | B101: Aug | C101: =B12 -> 5900 | D101: =AVERAGE(B10:B11) -> 5850 | E101: =AVERAGE(B9:B11) -> 5633.3333 | F101: =AVERAGE(B8:B11) -> 5425 | G101: =AVERAGE(B7:B11) -> 5260 | H101: =AVERAGE(B6:B11) -> 5050 | J101: =C101 -> 5900 | K101: =SUMIFS(Raw_Dataset!$D$2:$D$37,Raw_Dataset!$A$2:$A$37,B101,Raw_Dataset!$B$2:$B$37,"Nile Espresso") -> 6200 | L101: =J101-K101 -> -300 | M101: =ABS(L101) -> 300 | N101: =L101^2 -> 90000
A102: =A13 -> 9 | B102: Sep | C102: =B13 -> 5500 | D102: =AVERAGE(B11:B12) -> 6000 | E102: =AVERAGE(B10:B12) -> 5866.6667 | F102: =AVERAGE(B9:B12) -> 5700 | G102: =AVERAGE(B8:B12) -> 5520 | H102: =AVERAGE(B7:B12) -> 5366.6667 | J102: =C102 -> 5500 | K102: =SUMIFS(Raw_Dataset!$D$2:$D$37,Raw_Dataset!$A$2:$A$37,B102,Raw_Dataset!$B$2:$B$37,"Nile Espresso") -> 5700 | L102: =J102-K102 -> -200 | M102: =ABS(L102) -> 200 | N102: =L102^2 -> 40000
A103: =A14 -> 10 | B103: Oct | C103: =B14 -> 6200 | D103: =AVERAGE(B12:B13) -> 5700 | E103: =AVERAGE(B11:B13) -> 5833.3333 | F103: =AVERAGE(B10:B13) -> 5775 | G103: =AVERAGE(B9:B13) -> 5660 | H103: =AVERAGE(B8:B13) -> 5516.6667 | J103: =C103 -> 6200 | K103: =SUMIFS(Raw_Dataset!$D$2:$D$37,Raw_Dataset!$A$2:$A$37,B103,Raw_Dataset!$B$2:$B$37,"Nile Espresso") -> 5800 | L103: =J103-K103 -> 400 | M103: =ABS(L103) -> 400 | N103: =L103^2 -> 160000
A104: =A15 -> 11 | B104: Nov | C104: =B15 -> 6800 | D104: =AVERAGE(B13:B14) -> 5850 | E104: =AVERAGE(B12:B14) -> 5866.6667 | F104: =AVERAGE(B11:B14) -> 5925 | G104: =AVERAGE(B10:B14) -> 5860 | H104: =AVERAGE(B9:B14) -> 5750 | J104: =C104 -> 6800 | K104: =SUMIFS(Raw_Dataset!$D$2:$D$37,Raw_Dataset!$A$2:$A$37,B104,Raw_Dataset!$B$2:$B$37,"Nile Espresso") -> 6500 | L104: =J104-K104 -> 300 | M104: =ABS(L104) -> 300 | N104: =L104^2 -> 90000
A105: =A16 -> 12 | B105: Dec | C105: =B16 -> 7600 | D105: =AVERAGE(B14:B15) -> 6500 | E105: =AVERAGE(B13:B15) -> 6166.6667 | F105: =AVERAGE(B12:B15) -> 6100 | G105: =AVERAGE(B11:B15) -> 6100 | H105: =AVERAGE(B10:B15) -> 6016.6667 | J105: =C105 -> 7600 | K105: =SUMIFS(Raw_Dataset!$D$2:$D$37,Raw_Dataset!$A$2:$A$37,B105,Raw_Dataset!$B$2:$B$37,"Nile Espresso") -> 7200 | L105: =J105-K105 -> 400 | M105: =ABS(L105) -> 400 | N105: =L105^2 -> 160000
C107: MAD | D107: =(ABS(C100-D100)+ABS(C101-D101)+ABS(C102-D102)+ABS(C103-D103)+ABS(C104-D104)+ABS(C105-D105))/COUNT(C100:C105) -> 633.33333 | E107: =(ABS(C100-E100)+ABS(C101-E101)+ABS(C102-E102)+ABS(C103-E103)+ABS(C104-E104)+ABS(C105-E105))/COUNT(C100:C105) -> 711.11111 | F107: =(ABS(C100-F100)+ABS(C101-F101)+ABS(C102-F102)+ABS(C103-F103)+ABS(C104-F104)+ABS(C105-F105))/COUNT(C100:C105) -> 754.16667 | G107: =(ABS(C100-G100)+ABS(C101-G101)+ABS(C102-G102)+ABS(C103-G103)+ABS(C104-G104)+ABS(C105-G105))/COUNT(C100:C105) -> 816.66667 | H107: =(ABS(C100-H100)+ABS(C101-H101)+ABS(C102-H102)+ABS(C103-H103)+ABS(C104-H104)+ABS(C105-H105))/COUNT(C100:C105) -> 944.44444
C108: MSE | D108: =((C100-D100)^2+(C101-D101)^2+(C102-D102)^2+(C103-D103)^2+(C104-D104)^2+(C105-D105)^2)/COUNT(C100:C105) -> 517500 | E108: =((C100-E100)^2+(C101-E101)^2+(C102-E102)^2+(C103-E103)^2+(C104-E104)^2+(C105-E105)^2)/COUNT(C100:C105) -> 679259.26 | F108: =((C100-F100)^2+(C101-F101)^2+(C102-F102)^2+(C103-F103)^2+(C104-F104)^2+(C105-F105)^2)/COUNT(C100:C105) -> 760729.17 | G108: =((C100-G100)^2+(C101-G101)^2+(C102-G102)^2+(C103-G103)^2+(C104-G104)^2+(C105-G105)^2)/COUNT(C100:C105) -> 903800 | H108: =((C100-H100)^2+(C101-H101)^2+(C102-H102)^2+(C103-H103)^2+(C104-H104)^2+(C105-H105)^2)/COUNT(C100:C105) -> 1114074.1
A132: Cairo House Blend — Demand analysis and forecasting
A134: Period | B134: Sales (units) | C134: Month
A135: 1 | B135: =SUMIFS(Raw_Dataset!$C$2:$C$37,Raw_Dataset!$A$2:$A$37,C135,Raw_Dataset!$B$2:$B$37,"Cairo House Blend") -> 6000 | C135: Jan
A136: 2 | B136: =SUMIFS(Raw_Dataset!$C$2:$C$37,Raw_Dataset!$A$2:$A$37,C136,Raw_Dataset!$B$2:$B$37,"Cairo House Blend") -> 5800 | C136: Feb
A137: 3 | B137: =SUMIFS(Raw_Dataset!$C$2:$C$37,Raw_Dataset!$A$2:$A$37,C137,Raw_Dataset!$B$2:$B$37,"Cairo House Blend") -> 6500 | C137: Mar
A138: 4 | B138: =SUMIFS(Raw_Dataset!$C$2:$C$37,Raw_Dataset!$A$2:$A$37,C138,Raw_Dataset!$B$2:$B$37,"Cairo House Blend") -> 6800 | C138: Apr
A139: 5 | B139: =SUMIFS(Raw_Dataset!$C$2:$C$37,Raw_Dataset!$A$2:$A$37,C139,Raw_Dataset!$B$2:$B$37,"Cairo House Blend") -> 7200 | C139: May
A140: 6 | B140: =SUMIFS(Raw_Dataset!$C$2:$C$37,Raw_Dataset!$A$2:$A$37,C140,Raw_Dataset!$B$2:$B$37,"Cairo House Blend") -> 7600 | C140: Jun
A141: 7 | B141: =SUMIFS(Raw_Dataset!$C$2:$C$37,Raw_Dataset!$A$2:$A$37,C141,Raw_Dataset!$B$2:$B$37,"Cairo House Blend") -> 8200 | C141: Jul
A142: 8 | B142: =SUMIFS(Raw_Dataset!$C$2:$C$37,Raw_Dataset!$A$2:$A$37,C142,Raw_Dataset!$B$2:$B$37,"Cairo House Blend") -> 8000 | C142: Aug
A143: 9 | B143: =SUMIFS(Raw_Dataset!$C$2:$C$37,Raw_Dataset!$A$2:$A$37,C143,Raw_Dataset!$B$2:$B$37,"Cairo House Blend") -> 7500 | C143: Sep
A144: 10 | B144: =SUMIFS(Raw_Dataset!$C$2:$C$37,Raw_Dataset!$A$2:$A$37,C144,Raw_Dataset!$B$2:$B$37,"Cairo House Blend") -> 8400 | C144: Oct
A145: 11 | B145: =SUMIFS(Raw_Dataset!$C$2:$C$37,Raw_Dataset!$A$2:$A$37,C145,Raw_Dataset!$B$2:$B$37,"Cairo House Blend") -> 9100 | C145: Nov
A146: 12 | B146: =SUMIFS(Raw_Dataset!$C$2:$C$37,Raw_Dataset!$A$2:$A$37,C146,Raw_Dataset!$B$2:$B$37,"Cairo House Blend") -> 10200 | C146: Dec
A149: Simple moving average | F149: Window (months): | J149: =INDEX(D228:H228,1,MATCH(MIN(D238:H238),D238:H238,0)) -> 2
A151: Period | B151: Demand | D151: Forecast | E151: Error (A-F) | F151: |Error| | G151: Error^2
...
